evtool/__init__.py
evtool/mdl.py
evtool/plt.py
evtool-0.0.4.dist-info/licenses/LICENCE
evtool-0.0.4.dist-info/METADATA
evtool-0.0.4.dist-info/WHEEL
evtool-0.0.4.dist-info/top_level.txt
evtool-0.0.4.dist-info/RECORD
