Metadata-Version: 2.4
Name: evtool
Version: 0.0.4
Summary: Analyse and display output from the binary stellar-evolution code ev (a.k.a. STARS and TWIN).
Author-email: Marc van der Sluys <git@vandersluys.nl>
License-Expression: EUPL-1.2
Project-URL: GitHub, https://github.com/MarcvdSluys/evTool
Project-URL: ReadTheDocs, https://evtool.readthedocs.io
Keywords: astrophysics,stellar evolution,binary evolution,stellar model,binary model
Classifier: Development Status :: 3 - Alpha
Classifier: Intended Audience :: Developers
Classifier: Intended Audience :: Education
Classifier: Intended Audience :: Science/Research
Classifier: Natural Language :: English
Classifier: Operating System :: OS Independent
Classifier: Programming Language :: Python :: 3
Classifier: Topic :: Scientific/Engineering
Classifier: Topic :: Scientific/Engineering :: Astronomy
Classifier: Topic :: Scientific/Engineering :: Physics
License-File: LICENCE
Requires-Dist: pandas
Dynamic: license-file
